llm/__init__.py
llm/__main__.py
llm/cli.py
llm/embeddings.py
llm/embeddings_migrations.py
llm/errors.py
llm/hookspecs.py
llm/migrations.py
llm/models.py
llm/plugins.py
llm/py.typed
llm/templates.py
llm/tools.py
llm/utils.py
llm/default_plugins/__init__.py
llm/default_plugins/default_tools.py
llm/default_plugins/openai_models.py
llm-0.27.dist-info/licenses/LICENSE
llm-0.27.dist-info/METADATA
llm-0.27.dist-info/WHEEL
llm-0.27.dist-info/entry_points.txt
llm-0.27.dist-info/top_level.txt
llm-0.27.dist-info/RECORD
