Metadata-Version: 2.4
Name: llm
Version: 0.27
Summary: CLI utility and Python library for interacting with Large Language Models from organizations like OpenAI, Anthropic and Gemini plus local models installed on your own machine.
Author: Simon Willison
License-Expression: Apache-2.0
Project-URL: Homepage, https://github.com/simonw/llm
Project-URL: Documentation, https://llm.datasette.io/
Project-URL: Issues, https://github.com/simonw/llm/issues
Project-URL: CI, https://github.com/simonw/llm/actions
Project-URL: Changelog, https://github.com/simonw/llm/releases
Classifier: Development Status :: 4 - Beta
Classifier: Intended Audience :: Developers
Classifier: Intended Audience :: End Users/Desktop
Classifier: Intended Audience :: Science/Research
Classifier: Programming Language :: Python :: 3
Classifier: Programming Language :: Python :: 3.9
Classifier: Programming Language :: Python :: 3.10
Classifier: Programming Language :: Python :: 3.11
Classifier: Programming Language :: Python :: 3.12
Classifier: Programming Language :: Python :: 3.13
Classifier: Topic :: Scientific/Engineering :: Artificial Intelligence
Classifier: Topic :: Text Processing :: Linguistic
Classifier: Topic :: Utilities
Requires-Python: >=3.9
License-File: LICENSE
Requires-Dist: click
Requires-Dist: condense-json>=0.1.3
Requires-Dist: openai>=1.55.3
Requires-Dist: click-default-group>=1.2.3
Requires-Dist: sqlite-utils>=3.37
Requires-Dist: sqlite-migrate>=0.1a2
Requires-Dist: pydantic>=2.0.0
Requires-Dist: PyYAML
Requires-Dist: pluggy
Requires-Dist: python-ulid
Requires-Dist: setuptools
Requires-Dist: pip
Requires-Dist: pyreadline3; sys_platform == "win32"
Requires-Dist: puremagic
Provides-Extra: test
Requires-Dist: build; extra == "test"
Requires-Dist: click<8.2.0; extra == "test"
Requires-Dist: pytest; extra == "test"
Requires-Dist: numpy; extra == "test"
Requires-Dist: pytest-httpx>=0.33.0; extra == "test"
Requires-Dist: pytest-asyncio; extra == "test"
Requires-Dist: cogapp; extra == "test"
Requires-Dist: mypy>=1.10.0; extra == "test"
Requires-Dist: black>=25.1.0; extra == "test"
Requires-Dist: pytest-recording; extra == "test"
Requires-Dist: ruff; extra == "test"
Requires-Dist: syrupy; extra == "test"
Requires-Dist: types-click; extra == "test"
Requires-Dist: types-PyYAML; extra == "test"
Requires-Dist: types-setuptools; extra == "test"
Requires-Dist: llm-echo==0.3a3; extra == "test"
Dynamic: license-file
